sstudy/__init__.py
sstudy/core.py
sstudy-0.0.5.dist-info/LICENSE
sstudy-0.0.5.dist-info/METADATA
sstudy-0.0.5.dist-info/WHEEL
sstudy-0.0.5.dist-info/top_level.txt
sstudy-0.0.5.dist-info/RECORD
