Metadata-Version: 2.1
Name: sstudy
Version: 0.0.5
Summary: Simulation study storage
Home-page: UNKNOWN
Author: Marco Inacio
Author-email: pythonpackages@marcoinacio.com
License: GPL3
Keywords: simulation study
Platform: UNKNOWN
Requires-Dist: peewee
